{
  "schemaVersion": 1,
  "kit": "omarchy-native-kit",
  "appName": "zero-trust-access-review-console",
  "kind": "studio",
  "themeName": null,
  "files": [
    "src/omarchy-theme.css",
    "src/App.tsx",
    "src/styles.css",
    "src/main.tsx",
    "README.md"
  ],
  "layoutRegions": [
    {
      "name": "access-summary",
      "purpose": "Readiness counts for protected resources, healthy grants, review gates, and deny actions.",
      "tokens": [
        "surface",
        "surfaceRaised",
        "border",
        "accent"
      ]
    },
    {
      "name": "access-ledger",
      "purpose": "Protected resource inventory with owner, device posture gate, identity risk, and access state.",
      "tokens": [
        "background",
        "border",
        "shadow"
      ]
    },
    {
      "name": "risk-and-policy-panels",
      "purpose": "Identity risk, stale access exceptions, owner intent, exception windows, and rollback-safe zero-trust policy changes.",
      "tokens": [
        "surface",
        "surfaceForeground",
        "borderStrong",
        "info"
      ]
    }
  ],
  "components": [
    {
      "name": "ResourceAccessCard",
      "purpose": "Focusable protected resource card with owner, gate requirements, identity risk, and access state.",
      "tokens": [
        "surface",
        "surfaceRaised",
        "accent",
        "accentForeground"
      ],
      "interactions": [
        "focus outlines with accent",
        "state badge distinguishes allowed, review, and deny access",
        "gate requirements wrap without horizontal overflow"
      ]
    },
    {
      "name": "RiskFinding",
      "purpose": "Identity risk finding with resource subject, evidence, and access state.",
      "tokens": [
        "background",
        "border",
        "shadow"
      ],
      "interactions": [
        "focus state is visible for keyboard review",
        "deny candidates remain visually distinct"
      ]
    },
    {
      "name": "ZeroTrustPolicyChange",
      "purpose": "Zero-trust policy change with exception window, rollback guard, and access probe.",
      "tokens": [
        "surface",
        "foreground",
        "mutedForeground",
        "accent",
        "border"
      ],
      "interactions": [
        "tab order follows visual order",
        "rollback guidance wraps without horizontal overflow"
      ]
    }
  ],
  "acceptanceChecks": [
    "Generated app imports src/omarchy-theme.css before app styles.",
    "Every visible color comes from a --omarchy-* CSS variable or color-mix using one.",
    "Every button, row, input, and command item has a visible :focus-visible state.",
    "Layout remains stable at 320px, 768px, and 1280px viewport widths.",
    "Primary content is usable on first load without a marketing interstitial.",
    "A .desktop launcher can be generated with omarchy-native app desktop.",
    "An opt-in theme sync hook can be generated with omarchy-native app hook.",
    "npm run build completes successfully."
  ]
}
